README.md
setup.cfg
setup.py
adapt/__init__.py
adapt/_tree_utils.py
adapt/base.py
adapt/metrics.py
adapt/utils.py
adapt.egg-info/PKG-INFO
adapt.egg-info/SOURCES.txt
adapt.egg-info/dependency_links.txt
adapt.egg-info/not-zip-safe
adapt.egg-info/requires.txt
adapt.egg-info/top_level.txt
adapt/feature_based/__init__.py
adapt/feature_based/_adda.py
adapt/feature_based/_ccsa.py
adapt/feature_based/_cdan.py
adapt/feature_based/_coral.py
adapt/feature_based/_dann.py
adapt/feature_based/_deepcoral.py
adapt/feature_based/_fa.py
adapt/feature_based/_fmmd.py
adapt/feature_based/_mcd.py
adapt/feature_based/_mdd.py
adapt/feature_based/_pred.py
adapt/feature_based/_sa.py
adapt/feature_based/_tca.py
adapt/feature_based/_wdgrl.py
adapt/instance_based/__init__.py
adapt/instance_based/_balancedweighting.py
adapt/instance_based/_iwc.py
adapt/instance_based/_iwn.py
adapt/instance_based/_kliep.py
adapt/instance_based/_kmm.py
adapt/instance_based/_ldm.py
adapt/instance_based/_nearestneighborsweighting.py
adapt/instance_based/_rulsif.py
adapt/instance_based/_tradaboost.py
adapt/instance_based/_ulsif.py
adapt/instance_based/_wann.py
adapt/parameter_based/__init__.py
adapt/parameter_based/_finetuning.py
adapt/parameter_based/_linint.py
adapt/parameter_based/_regular.py
adapt/parameter_based/_transfer_tree.py