Metadata-Version: 2.1
Name: adapt
Version: 0.4.4
Summary: Awesome Domain Adaptation Python Toolbox for Tensorflow and Scikit-learn
Home-page: https://github.com/adapt-python/adapt.git
Author: Antoine de Mathelin
Author-email: antoine.demat@gmail.com
License: BSD-2
Platform: UNKNOWN
